git_clog.py
git_clog-0.3.0.dist-info/LICENSE
git_clog-0.3.0.dist-info/METADATA
git_clog-0.3.0.dist-info/WHEEL
git_clog-0.3.0.dist-info/entry_points.txt
git_clog-0.3.0.dist-info/top_level.txt
git_clog-0.3.0.dist-info/RECORD
